<?xml version="1.0" encoding="UTF-8"?>

<LanguageData>
<!--=============== Biophormids ====================-->
<!--=============== Labryscid ====================-->
<OE_Labryscid.label>лабрисцид</OE_Labryscid.label>
<OE_Labryscid.labelPlural>лабрисциды</OE_Labryscid.labelPlural>

<OE_Labryscid.lifeStages.0.label>личинка лабрисцида</OE_Labryscid.lifeStages.0.label>
<OE_Labryscid.lifeStages.0.labelPlural>личинки лабрисцида</OE_Labryscid.lifeStages.0.labelPlural>

<!--=============== Razorsythe ====================-->
<OE_Razorsythe.label>бритвокрыл</OE_Razorsythe.label>
<OE_Razorsythe.labelPlural>бритвокрылы</OE_Razorsythe.labelPlural>

<OE_Razorsythe.lifeStages.0.label>личинка бритвокрыла</OE_Razorsythe.lifeStages.0.label>
<OE_Razorsythe.lifeStages.0.labelPlural>личинки бритвокрыла</OE_Razorsythe.lifeStages.0.labelPlural>

<!--=============== Winglance ====================-->
<OE_Winglance.label>винглэнс</OE_Winglance.label>
<OE_Winglance.labelPlural>винглэнсы</OE_Winglance.labelPlural>

<OE_Winglance.lifeStages.0.label>личинка винглэнса</OE_Winglance.lifeStages.0.label>
<OE_Winglance.lifeStages.0.labelPlural>личинки винглэнса</OE_Winglance.lifeStages.0.labelPlural>

<!--=============== Brontarok ====================-->
<OE_Brontarok.label>бронтарок</OE_Brontarok.label>
<OE_Brontarok.labelPlural>бронтароки</OE_Brontarok.labelPlural>

<OE_Brontarok.lifeStages.0.label>личинка бронтарока</OE_Brontarok.lifeStages.0.label>
<OE_Brontarok.lifeStages.0.labelPlural>личинки бронтарока</OE_Brontarok.lifeStages.0.labelPlural>

<!--=============== Swarmella ====================-->
<OE_Swarmella.label>свармелла</OE_Swarmella.label>
<OE_Swarmella.labelPlural>свармеллы</OE_Swarmella.labelPlural>

<OE_Swarmella.lifeStages.0.label>личинка свармеллы</OE_Swarmella.lifeStages.0.label>
<OE_Swarmella.lifeStages.0.labelPlural>личинки свармеллы</OE_Swarmella.lifeStages.0.labelPlural>

<!--=============== Pincerlin ====================-->
<OE_Pincerlin.label>пинцерлин</OE_Pincerlin.label>
<OE_Pincerlin.labelPlural>пинцерлины</OE_Pincerlin.labelPlural>

<OE_Pincerlin.lifeStages.0.label>личинка пинцерлина</OE_Pincerlin.lifeStages.0.label>
<OE_Pincerlin.lifeStages.0.labelPlural>личинки пинцерлина</OE_Pincerlin.lifeStages.0.labelPlural>

<!--=============== Monarchid ====================-->
<OE_Monarchid.label>монархид</OE_Monarchid.label>
<OE_Monarchid.labelPlural>монархиды</OE_Monarchid.labelPlural>

<OE_Monarchid.lifeStages.0.label>личинка монархида</OE_Monarchid.lifeStages.0.label>
<OE_Monarchid.lifeStages.0.labelPlural>личинки монархида</OE_Monarchid.lifeStages.0.labelPlural>

</LanguageData>