<?xml version="1.0" encoding="utf-8" ?>

<LanguageData>
<!--=============== Remove Death Acidifier ====================-->
<OE_RemoveDeathAcidifier.label>видалити - смертельний окислювач</OE_RemoveDeathAcidifier.label>
<OE_RemoveDeathAcidifier.description>Видалити - смертельний окислювач.</OE_RemoveDeathAcidifier.description>
<OE_RemoveDeathAcidifier.jobString>Видалення - смертельний окислювач.</OE_RemoveDeathAcidifier.jobString>
<OE_RemoveDeathAcidifier.successfullyRemovedHediffMessage>{0} успішно видалив смертельний окислювач з {1}.</OE_RemoveDeathAcidifier.successfullyRemovedHediffMessage>

<!--=============== Biophormids Pherocore Buff ====================-->
<OE_AdministerBiophormidsPherocore.label>ввести фероядро Біоформіди</OE_AdministerBiophormidsPherocore.label>
<OE_AdministerBiophormidsPherocore.description>Введіть концентровану дозу фероядра Біоформіди, щоб посилити пішака.</OE_AdministerBiophormidsPherocore.description>
<OE_AdministerBiophormidsPherocore.jobString>Введіть концентровану дозу фероядра Біоформіди, щоб посилити пішака.</OE_AdministerBiophormidsPherocore.jobString>

</LanguageData>