<?xml version="1.0" encoding="utf-8" ?>

<LanguageData>
<!--=============== Boots - Military ====================-->
<OE_Footwear_Military.label>obsidia military boots</OE_Footwear_Military.label>
<OE_Footwear_Military.description>Military boots, perfectly protects and providing advanced skin sense feedback to the wearer. Designed for use by all Obsidia Empire militaries.</OE_Footwear_Military.description>

<!--=============== Boots - Worker ====================-->
<OE_Footwear_Worker.label>obsidia worker boots</OE_Footwear_Worker.label>
<OE_Footwear_Worker.description>Worker boots, good protects and providing performance improvement to the wearer. Designed for use by all Obsidia Empire workers.</OE_Footwear_Worker.description>

<!--=============== Gloves - Military ====================-->
<OE_Handwear_Military.label>obsidia military gloves</OE_Handwear_Military.label>
<OE_Handwear_Military.description>Military gloves, perfectly protects and providing advanced skin sense feedback to the wearer. Designed for use by all Obsidia Empire militaries.</OE_Handwear_Military.description>

<!--=============== Gloves - Worker ====================-->
<OE_Handwear_Worker.label>obsidia worker gloves</OE_Handwear_Worker.label>
<OE_Handwear_Worker.description>Worker gloves, good protects and providing performance improvement to the wearer. Designed for use by all Obsidia Empire workers.</OE_Handwear_Worker.description>

</LanguageData>