<?xml version="1.0" encoding="utf-8" ?>

<LanguageData>
<!--=============== Implant - Evolution Power Stone ====================-->
<OE_ImplantPowerStone_Evolution.label>Evolution Power Stone</OE_ImplantPowerStone_Evolution.label>
<OE_ImplantPowerStone_Evolution.description>An installed - Evolution Power Stone.</OE_ImplantPowerStone_Evolution.description>

<!--=============== Implant - Operator Power Stone ====================-->
<OE_ImplantPowerStone_Operator.label>Operator Power Stone</OE_ImplantPowerStone_Operator.label>
<OE_ImplantPowerStone_Operator.description>An installed - Operator Power Stone.</OE_ImplantPowerStone_Operator.description>

<!--=============== Implant - Champion Power Stone ====================-->
<OE_ImplantPowerStone_Champion.label>Champion Power Stone</OE_ImplantPowerStone_Champion.label>
<OE_ImplantPowerStone_Champion.description>An installed - Champion Power Stone.</OE_ImplantPowerStone_Champion.description>

<!--=============== Implant - Outrider Power Stone ====================-->
<OE_ImplantPowerStone_Outrider.label>Outrider Power Stone</OE_ImplantPowerStone_Outrider.label>
<OE_ImplantPowerStone_Outrider.description>An installed - Outrider Power Stone.</OE_ImplantPowerStone_Outrider.description>

<!--=============== Implant - Monarch Power Stone ====================-->
<OE_ImplantPowerStone_Monarch.label>Monarch Power Stone</OE_ImplantPowerStone_Monarch.label>
<OE_ImplantPowerStone_Monarch.description>An installed - Monarch Power Stone.</OE_ImplantPowerStone_Monarch.description>

<!--=============== Implant - Techmaster Power Stone ====================-->
<OE_ImplantPowerStone_Techmaster.label>Techmaster Power Stone</OE_ImplantPowerStone_Techmaster.label>
<OE_ImplantPowerStone_Techmaster.description>An installed - Techmaster Power Stone.</OE_ImplantPowerStone_Techmaster.description>

<!--=============== Implant - Undead Power Stone ====================-->
<OE_ImplantPowerStone_Undead.label>Undead Power Stone</OE_ImplantPowerStone_Undead.label>
<OE_ImplantPowerStone_Undead.description>An installed - Undead Power Stone.</OE_ImplantPowerStone_Undead.description>

</LanguageData>